autonn/__init__.py
autonn/_optimizer.py
autonn/_pprint.py
autonn/base.py
autonn/dataset.py
autonn/env.py
autonn/fields.py
autonn/loss_metric.py
autonn/nn.py
autonn/operator.py
autonn/oss.py
autonn/utils.py
autonn/resnet/__init__.py
autonn/resnet/_backend.py
autonn/resnet/base.py
autonn/sklearn/__init__.py
autonn/sklearn/svm.py
tests/__init__.py
tests/test_config_space.py
tests/test_datasets.py
tests/test_operator.py
tests/test_optimizer.py
tests/test_resnet.py
tests/test_utils.py
autonn-0.0.2.dist-info/METADATA
autonn-0.0.2.dist-info/WHEEL
autonn-0.0.2.dist-info/top_level.txt
autonn-0.0.2.dist-info/RECORD
